{
  "rsi": {
    "strategy": "rsi",
    "account_size": 100000.0,
    "equity": 99908.82,
    "balance": 100000.0,
    "today_start_equity": 100000.0,
    "current_day": "2026-06-03",
    "daily_realized_pnl": 0.0,
    "peak_balance": 100000.0,
    "status": "active",
    "failed_reason": "",
    "resolved_at": "",
    "sl_count": {},
    "trades_total": 0,
    "wins": 0,
    "losses": 0
  },
  "ema5": {
    "strategy": "ema5",
    "account_size": 100000.0,
    "equity": 100000.0,
    "balance": 100000.0,
    "today_start_equity": 100000.0,
    "current_day": "2026-06-03",
    "daily_realized_pnl": 0.0,
    "peak_balance": 100000.0,
    "status": "active",
    "failed_reason": "",
    "resolved_at": "",
    "sl_count": {},
    "trades_total": 0,
    "wins": 0,
    "losses": 0
  },
  "eth_blueprint": {
    "strategy": "eth_blueprint",
    "account_size": 100000.0,
    "equity": 100050.54,
    "balance": 100000.0,
    "today_start_equity": 100000.0,
    "current_day": "2026-06-03",
    "daily_realized_pnl": 0.0,
    "peak_balance": 100000.0,
    "status": "active",
    "failed_reason": "",
    "resolved_at": "",
    "sl_count": {},
    "trades_total": 0,
    "wins": 0,
    "losses": 0
  },
  "smt_divergence": {
    "strategy": "smt_divergence",
    "account_size": 100000.0,
    "equity": 101000.0,
    "balance": 101000.0,
    "today_start_equity": 99000.0,
    "current_day": "2026-06-03",
    "daily_realized_pnl": 2000.0,
    "peak_balance": 101000.0,
    "status": "active",
    "failed_reason": "",
    "resolved_at": "",
    "sl_count": {},
    "trades_total": 2,
    "wins": 1,
    "losses": 1
  },
  "jadecap": {
    "strategy": "jadecap",
    "account_size": 100000.0,
    "equity": 100756.02,
    "balance": 100756.02,
    "today_start_equity": 100256.02,
    "current_day": "2026-06-03",
    "daily_realized_pnl": 756.02,
    "peak_balance": 100756.02,
    "status": "active",
    "failed_reason": "",
    "resolved_at": "",
    "sl_count": {},
    "trades_total": 1,
    "wins": 1,
    "losses": 0
  },
  "quantx": {
    "strategy": "quantx",
    "account_size": 100000.0,
    "equity": 98000.0,
    "balance": 98000.0,
    "today_start_equity": 99000.0,
    "current_day": "2026-06-03",
    "daily_realized_pnl": -1000.0,
    "peak_balance": 100000.0,
    "status": "active",
    "failed_reason": "",
    "resolved_at": "",
    "sl_count": {
      "quantx": 1
    },
    "trades_total": 2,
    "wins": 0,
    "losses": 2
  }
}